LICENSE
pyproject.toml
telescope/__init__.py
telescope/app.py
telescope/cli.py
telescope/filters/__init__.py
telescope/filters/duplicates.py
telescope/filters/filter.py
telescope/filters/length.py
telescope/filters/ner.py
telescope/filters/terminology.py
telescope/metrics/__init__.py
telescope/metrics/bertscore/__init__.py
telescope/metrics/bertscore/metric.py
telescope/metrics/bertscore/result.py
telescope/metrics/bleurt/__init__.py
telescope/metrics/bleurt/metric.py
telescope/metrics/bleurt/result.py
telescope/metrics/chrf/__init__.py
telescope/metrics/chrf/metric.py
telescope/metrics/chrf/result.py
telescope/metrics/comet/__init__.py
telescope/metrics/comet/metric.py
telescope/metrics/comet/result.py
telescope/metrics/gleu/__init__.py
telescope/metrics/gleu/metric.py
telescope/metrics/meteor/__init__.py
telescope/metrics/meteor/metric.py
telescope/metrics/meteor/result.py
telescope/metrics/metric.py
telescope/metrics/prism/__init__.py
telescope/metrics/prism/metric.py
telescope/metrics/prism/result.py
telescope/metrics/result.py
telescope/metrics/sacrebleu/__init__.py
telescope/metrics/sacrebleu/metric.py
telescope/metrics/sacrebleu/result.py
telescope/metrics/ter/__init__.py
telescope/metrics/ter/metric.py
telescope/metrics/ter/result.py
telescope/metrics/utils.py
telescope/metrics/zero_edit/__init__.py
telescope/metrics/zero_edit/metric.py
telescope/metrics/zero_edit/result.py
telescope/plotting.py
telescope/testset.py
telescope/utils.py
mt_telescope-0.0.2.dist-info/entry_points.txt
mt_telescope-0.0.2.dist-info/LICENSE
mt_telescope-0.0.2.dist-info/WHEEL
mt_telescope-0.0.2.dist-info/METADATA
mt_telescope-0.0.2.dist-info/RECORD
