Metadata-Version: 2.1
Name: mt-telescope
Version: 0.0.2
Summary: A visual platform for contrastive evaluation of machine translation systems
Home-page: https://github.com/Unbabel/MT-Telescope
License: Apache-2.0
Keywords: Machine Translation,Evaluation,Unbabel
Author: Ricardo Rei, Craig Stewart, Catarina Farinha, Alon Lavie
Requires-Python: >=3.7.0,<4.0.0
Classifier: Development Status :: 4 - Beta
Classifier: Environment :: Console
Classifier: Intended Audience :: Science/Research
Classifier: License :: OSI Approved :: Apache Software License
Classifier: Programming Language :: Python :: 3
Classifier: Programming Language :: Python :: 3.10
Classifier: Programming Language :: Python :: 3.7
Classifier: Programming Language :: Python :: 3.8
Classifier: Programming Language :: Python :: 3.9
Classifier: Topic :: Scientific/Engineering :: Artificial Intelligence
Requires-Dist: bert-score (>=0.3.7)
Requires-Dist: numpy (>=1.20.0)
Requires-Dist: plotly (>=4.14.3,<5.0.0)
Requires-Dist: pytorch-nlp (==0.5.0)
Requires-Dist: sacrebleu (>=2.0.0)
Requires-Dist: scipy (>=1.5.4)
Requires-Dist: stanza (>=1.2)
Requires-Dist: streamlit (>=0.79.0,<0.80.0)
Requires-Dist: unbabel-comet (==1.0.1)
Project-URL: Documentation, https://github.com/Unbabel/MT-Telescope/README.md
Project-URL: Repository, https://github.com/Unbabel/MT-Telescope
